bingo_elastic/__init__.py
bingo_elastic/elastic.py
bingo_elastic/queries.py
bingo_elastic/utils.py
bingo_elastic/model/__init__.py
bingo_elastic/model/helpers.py
bingo_elastic/model/record.py
bingo_elastic-1.36.1.dist-info/METADATA
bingo_elastic-1.36.1.dist-info/WHEEL
bingo_elastic-1.36.1.dist-info/top_level.txt
bingo_elastic-1.36.1.dist-info/RECORD
